skills_for_all_agent/__init__.py
skills_for_all_agent/skill_tool.py
skills_for_all_agent/skills/algorithmic-art/LICENSE.txt
skills_for_all_agent/skills/algorithmic-art/SKILL.md
skills_for_all_agent/skills/algorithmic-art/templates/generator_template.js
skills_for_all_agent/skills/algorithmic-art/templates/viewer.html
skills_for_all_agent/skills/brand-guidelines/LICENSE.txt
skills_for_all_agent/skills/brand-guidelines/SKILL.md
skills_for_all_agent/skills/c_2_ast/SKILL.md
skills_for_all_agent/skills/c_2_ast/reference.md
skills_for_all_agent/skills/c_2_ast/scripts/c_2_ast.py
skills_for_all_agent/skills/c_2_ast/scripts/save_c.py
skills_for_all_agent/skills/c_2_ast/scripts/source.c
skills_for_all_agent/skills/c_2_ast/scripts/temp.c
skills_for_all_agent/skills/c_2_ast/scripts/test.c
skills_for_all_agent/skills/canvas-design/LICENSE.txt
skills_for_all_agent/skills/canvas-design/SKILL.md
skills_for_all_agent/skills/canvas-design/canvas-fonts/ArsenalSC-OFL.txt
skills_for_all_agent/skills/canvas-design/canvas-fonts/ArsenalSC-Regular.ttf
skills_for_all_agent/skills/canvas-design/canvas-fonts/BigShoulders-Bold.ttf
skills_for_all_agent/skills/canvas-design/canvas-fonts/BigShoulders-OFL.txt
skills_for_all_agent/skills/canvas-design/canvas-fonts/BigShoulders-Regular.ttf
skills_for_all_agent/skills/canvas-design/canvas-fonts/Boldonse-OFL.txt
skills_for_all_agent/skills/canvas-design/canvas-fonts/Boldonse-Regular.ttf
skills_for_all_agent/skills/canvas-design/canvas-fonts/BricolageGrotesque-Bold.ttf
skills_for_all_agent/skills/canvas-design/canvas-fonts/BricolageGrotesque-OFL.txt
skills_for_all_agent/skills/canvas-design/canvas-fonts/BricolageGrotesque-Regular.ttf
skills_for_all_agent/skills/canvas-design/canvas-fonts/CrimsonPro-Bold.ttf
skills_for_all_agent/skills/canvas-design/canvas-fonts/CrimsonPro-Italic.ttf
skills_for_all_agent/skills/canvas-design/canvas-fonts/CrimsonPro-OFL.txt
skills_for_all_agent/skills/canvas-design/canvas-fonts/CrimsonPro-Regular.ttf
skills_for_all_agent-0.1.1.dist-info/METADATA
skills_for_all_agent-0.1.1.dist-info/WHEEL
skills_for_all_agent-0.1.1.dist-info/top_level.txt
skills_for_all_agent-0.1.1.dist-info/RECORD
