Metadata-Version: 2.4
Name: skills-for-all-agent
Version: 0.1.1
Summary: Lightweight skill loader and runner for agent function calling.
Author: LLK
License: MIT
Project-URL: Homepage, https://example.com
Project-URL: Repository, https://example.com
Project-URL: Issues, https://example.com/issues
Keywords: agent,skills,tooling,function-calling
Classifier: Development Status :: 3 - Alpha
Classifier: Intended Audience :: Developers
Classifier: Programming Language :: Python :: 3
Classifier: Programming Language :: Python :: 3 :: Only
Classifier: Programming Language :: Python :: 3.8
Classifier: Programming Language :: Python :: 3.9
Classifier: Programming Language :: Python :: 3.10
Classifier: Programming Language :: Python :: 3.11
Classifier: Programming Language :: Python :: 3.12
Classifier: Topic :: Software Development :: Libraries
Classifier: Topic :: Software Development :: Libraries :: Python Modules
Requires-Python: >=3.8
Provides-Extra: langchain
Requires-Dist: langchain>=0.1.0; extra == "langchain"
Requires-Dist: langchain-community>=0.1.0; extra == "langchain"
Requires-Dist: pydantic>=2.0.0; extra == "langchain"
